flask_wtfgen/__init__.py
flask_wtfgen/markup.py
Flask_WTFGen-0.2.dist-info/LICENSE
Flask_WTFGen-0.2.dist-info/METADATA
Flask_WTFGen-0.2.dist-info/WHEEL
Flask_WTFGen-0.2.dist-info/top_level.txt
Flask_WTFGen-0.2.dist-info/zip-safe
Flask_WTFGen-0.2.dist-info/RECORD
